textminer_pro/__init__.py
textminer_pro/keywords.py
textminer_pro/language.py
textminer_pro/preprocessing.py
textminer_pro/summary.py
textminer_pro_jys-0.1.5.dist-info/METADATA
textminer_pro_jys-0.1.5.dist-info/WHEEL
textminer_pro_jys-0.1.5.dist-info/top_level.txt
textminer_pro_jys-0.1.5.dist-info/RECORD
