Metadata-Version: 2.4
Name: textminer-pro-jys
Version: 0.1.5
Summary: Advanced text mining utils
Requires-Dist: nltk>=3.8
Requires-Dist: scikit-learn>=1.4
Requires-Dist: sumy>=0.11
Requires-Dist: langdetect>=1.0
Dynamic: description
Dynamic: description-content-type
Dynamic: requires-dist
Dynamic: summary
